odoo/addons/account_cutoff_accrual_purchase_stock/README.rst
odoo/addons/account_cutoff_accrual_purchase_stock/__init__.py
odoo/addons/account_cutoff_accrual_purchase_stock/__manifest__.py
odoo/addons/account_cutoff_accrual_purchase_stock/i18n/account_cutoff_accrual_purchase_stock.pot
odoo/addons/account_cutoff_accrual_purchase_stock/i18n/it.po
odoo/addons/account_cutoff_accrual_purchase_stock/models/__init__.py
odoo/addons/account_cutoff_accrual_purchase_stock/models/purchase_order_line.py
odoo/addons/account_cutoff_accrual_purchase_stock/readme/CONTRIBUTORS.rst
odoo/addons/account_cutoff_accrual_purchase_stock/readme/DESCRIPTION.rst
odoo/addons/account_cutoff_accrual_purchase_stock/static/description/icon.png
odoo/addons/account_cutoff_accrual_purchase_stock/static/description/index.html
odoo/addons/account_cutoff_accrual_purchase_stock/tests/__init__.py
odoo/addons/account_cutoff_accrual_purchase_stock/tests/common.py
odoo/addons/account_cutoff_accrual_purchase_stock/tests/test_cutoff_expense.py
odoo_addon_account_cutoff_accrual_purchase_stock-16.0.1.1.0.dist-info/METADATA
odoo_addon_account_cutoff_accrual_purchase_stock-16.0.1.1.0.dist-info/WHEEL
odoo_addon_account_cutoff_accrual_purchase_stock-16.0.1.1.0.dist-info/top_level.txt
odoo_addon_account_cutoff_accrual_purchase_stock-16.0.1.1.0.dist-info/RECORD
